moveck_bridge_btk/__init__.py
moveck_bridge_btk/_btkPY.so
moveck_bridge_btk/cacert.pem
moveck_bridge_btk/libkaleido_core.0.19.dylib
moveck_bridge_btk/libkaleido_crypto.0.19.dylib
moveck_bridge_btk/libkaleido_libcurl.0.19.dylib
moveck_bridge_btk/libkaleido_network.0.19.dylib
moveck_bridge_btk/libkaleido_ssl.0.19.dylib
moveck_bridge_btk/libkaleido_templer.0.19.dylib
moveck_bridge_btk/libvitruvi_core.0.17.dylib
moveck_bridge_btk/plugins/mck-vitruvi_c3d-format.so
moveck_bridge_btk/plugins/mck-vitruvi_classical-mechanics.so
moveck_bridge_btk/plugins/mck-vitruvi_data-modifier.so
moveck_bridge_btk/plugins/mck-vitruvi_signal.so
moveck_bridge_btk-2025.3.2.dist-info/METADATA
moveck_bridge_btk-2025.3.2.dist-info/WHEEL
moveck_bridge_btk-2025.3.2.dist-info/top_level.txt
moveck_bridge_btk-2025.3.2.dist-info/RECORD
