Metadata-Version: 2.4
Name: moveck_bridge_btk
Version: 2025.3.2
Summary: Moveck Bridge is the new Biomechanical ToolKit for Python3 with an improved API identical to the original one proposed for Matlab.
Author-email: Arnaud Barré <support@moveck.com>
Maintainer-email: "Moveck Solution inc." <support@moveck.com>
License: Last Updated:
Project-URL: Homepage, https://www.moveck.com
Project-URL: Documentation, https://www.moveck.com
Project-URL: Changelog, https://www.moveck.com
Keywords: Biomechanics,C3D,markers,mocap,Motion Capture,Motion Analysis,forceplate,force platform,EMG,electromyography,IMU,Inertial Measurement Unit,Marker-based,Markerless
Classifier: Programming Language :: Python :: 3
Classifier: Development Status :: 4 - Beta
Classifier: Environment :: Console
Classifier: Intended Audience :: Developers
Classifier: Intended Audience :: Education
Classifier: Intended Audience :: Information Technology
Classifier: Intended Audience :: Science/Research
Classifier: License :: Other/Proprietary License
Classifier: Natural Language :: English
Requires-Python: >=3.9.0
Requires-Dist: numpy>=2.0.2
Dynamic: requires-dist
